Metadata-Version: 2.1
Name: fasttext-language-detection
Version: 0.4
Summary: Language detection wrapper with fasttext
Home-page: https://github.com/lang-ai/fasttext-language-detection
Author: Alberto Ezpondaburu
Author-email: aezpondaburu@lang.ai 
License: MIT
Keywords: language detection,language identification,fasttext
Classifier: Programming Language :: Python :: 3
Classifier: Operating System :: OS Independent
License-File: LICENSE
